mkdocs_behave/__about__.py
mkdocs_behave/__init__.py
mkdocs_behave/featureformatter.py
mkdocs_behave/plugin.py
mkdocs_behave-1.0.0.dist-info/METADATA
mkdocs_behave-1.0.0.dist-info/WHEEL
mkdocs_behave-1.0.0.dist-info/entry_points.txt
mkdocs_behave-1.0.0.dist-info/licenses/LICENCE.txt
mkdocs_behave-1.0.0.dist-info/RECORD
