Metadata-Version: 2.1
Name: mkdocs-behave
Version: 1.0.0
Summary: A MkDocs plugin to render behave feature files
Project-URL: Documentation, https://github.com/mjayfrancis/mkdocs-behave#readme
Project-URL: Issues, https://github.com/mjayfrancis/mkdocs-behave/issues
Project-URL: Source, https://github.com/mjayfrancis/mkdocs-behave
Author-email: Matthew Francis <mjay.francis@gmail.com>
License-Expression: MIT
License-File: LICENCE.txt
Classifier: Development Status :: 4 - Beta
Classifier: Programming Language :: Python
Classifier: Programming Language :: Python :: 3.8
Classifier: Programming Language :: Python :: 3.9
Classifier: Programming Language :: Python :: 3.10
Classifier: Programming Language :: Python :: 3.11
Classifier: Programming Language :: Python :: Implementation :: CPython
Classifier: Programming Language :: Python :: Implementation :: PyPy
Requires-Python: >=3.8
Requires-Dist: behave==1.2.6
Requires-Dist: mkdocs>=1.5.3
